lamberthub/__init__.py
lamberthub/linalg.py
lamberthub/ecc_solvers/__init__.py
lamberthub/ecc_solvers/avanzini.py
lamberthub/ecc_solvers/utils.py
lamberthub/p_solvers/__init__.py
lamberthub/p_solvers/battin.py
lamberthub/p_solvers/gauss.py
lamberthub/universal_solvers/__init__.py
lamberthub/universal_solvers/arora.py
lamberthub/universal_solvers/gooding.py
lamberthub/universal_solvers/izzo.py
lamberthub/universal_solvers/vallado.py
lamberthub/utils/__init__.py
lamberthub/utils/angles.py
lamberthub/utils/assertions.py
lamberthub/utils/elements.py
lamberthub/utils/kepler.py
lamberthub/utils/stumpff.py
lamberthub-1.0.0.dist-info/LICENSE
lamberthub-1.0.0.dist-info/WHEEL
lamberthub-1.0.0.dist-info/METADATA
lamberthub-1.0.0.dist-info/RECORD
