Metadata-Version: 2.1
Name: lamberthub
Version: 1.0.0
Summary: A collection of Lambert's problem solvers.
Keywords: aerospace,astrodynamics,orbital-mechanics,kepler,lambert,orbit-determination
Author-email: Jorge Martínez Garrido <contact@jorgemartinez.space>
Maintainer-email: Jorge Martínez Garrido <contact@jorgemartinez.space>
Requires-Python: >=3.10
Classifier: License :: OSI Approved :: Apache Software License
Classifier: Development Status :: 4 - Beta
Classifier: Intended Audience :: Education
Classifier: Intended Audience :: Science/Research
Classifier: Operating System :: OS Independent
Classifier: Programming Language :: Python
Classifier: Programming Language :: Python :: 3
Classifier: Programming Language :: Python :: 3.10
Classifier: Programming Language :: Python :: 3.11
Classifier: Programming Language :: Python :: 3.12
Classifier: Programming Language :: Python :: Implementation :: CPython
Classifier: Topic :: Scientific/Engineering
Classifier: Topic :: Scientific/Engineering :: Physics
Classifier: Topic :: Scientific/Engineering :: Astronomy
Requires-Dist: numba
Requires-Dist: numpy
Requires-Dist: scipy
Requires-Dist: pytest==8.3.3 ; extra == "tests"
Requires-Dist: pytest-cov==5.0.0 ; extra == "tests"
Project-URL: Documentation, https://github.com/jorgepiloto/lamberthub/blob/main/README.md
Project-URL: Homepage, https://github.com/jorgepiloto/lamberthub
Project-URL: Issues, https://github.com/jorgepiloto/lamberthub/issues
Project-URL: Releases, https://github.com/jorgepiloto/lamberthub/releases
Project-URL: Source, https://github.com/jorgepiloto/lamberthub
Provides-Extra: tests
